pipefish/__init__.py
pipefish/__main__.py
pipefish/process_cobertura.py
pipefish/process_junit.py
pipefish/version.py
pipefish-0.4.2.dist-info/LICENSE
pipefish-0.4.2.dist-info/METADATA
pipefish-0.4.2.dist-info/WHEEL
pipefish-0.4.2.dist-info/top_level.txt
pipefish-0.4.2.dist-info/RECORD
